cocotbext/__init__.py
cocotbext/hyperbus/__init__.py
cocotbext/hyperbus/hbc_fsm.py
cocotbext/hyperbus/hyperbus_controller.py
cocotbext/hyperbus/templates/.gitkeep
cocotbext_hyperbus-0.2.5.dist-info/METADATA
cocotbext_hyperbus-0.2.5.dist-info/WHEEL
cocotbext_hyperbus-0.2.5.dist-info/entry_points.txt
cocotbext_hyperbus-0.2.5.dist-info/licenses/LICENSE
cocotbext_hyperbus-0.2.5.dist-info/RECORD
