Metadata-Version: 2.1
Name: cocotbext-hyperbus
Version: 0.2.5
Summary: COCOTB VIP for hyperbus protocol
Author-Email: Meet Sangani <meet.sangani@outlook.com>
Maintainer-Email: Vijayvithal Jahagirdar <jvs@dyumnin.com>, HaIIucination <karthik22kallakuri@gmail.com>, Likhit <www.likhit.mangena@gmail.com>
Classifier: Development Status :: 4 - Beta
Classifier: Intended Audience :: Developers
Classifier: Programming Language :: Python :: 3.8
Project-URL: Homepage, https://Dyumnin-Interns.github.io/cocotbext_hyperbus
Project-URL: Repository, https://github.com/Dyumnin-Interns/cocotbext_hyperbus.git
Project-URL: Issues, https://github.com/Dyumnin-Interns/cocotbext_hyperbus/issues
Project-URL: Documentation, https://Dyumnin-Interns.github.io/cocotbext_hyperbus
Requires-Python: >=3.9
Requires-Dist: cocotb
